odoo/addons/shopinvader_sale_profile/README.rst
odoo/addons/shopinvader_sale_profile/__init__.py
odoo/addons/shopinvader_sale_profile/__manifest__.py
odoo/addons/shopinvader_sale_profile/demo/account_fiscal_position.xml
odoo/addons/shopinvader_sale_profile/demo/shopinvader_sale_profile.xml
odoo/addons/shopinvader_sale_profile/i18n/shopinvader_sale_profile.pot
odoo/addons/shopinvader_sale_profile/models/__init__.py
odoo/addons/shopinvader_sale_profile/models/shopinvader_backend.py
odoo/addons/shopinvader_sale_profile/models/shopinvader_partner.py
odoo/addons/shopinvader_sale_profile/models/shopinvader_sale_profile.py
odoo/addons/shopinvader_sale_profile/models/shopinvader_variant.py
odoo/addons/shopinvader_sale_profile/readme/CONTRIBUTORS.rst
odoo/addons/shopinvader_sale_profile/readme/DESCRIPTION.rst
odoo/addons/shopinvader_sale_profile/security/shopinvader_sale_profile.xml
odoo/addons/shopinvader_sale_profile/static/description/index.html
odoo/addons/shopinvader_sale_profile/tests/__init__.py
odoo/addons/shopinvader_sale_profile/tests/test_customer_service.py
odoo/addons/shopinvader_sale_profile/tests/test_shopinvader_backend_sale_profile.py
odoo/addons/shopinvader_sale_profile/tests/test_shopinvader_sale_profile.py
odoo/addons/shopinvader_sale_profile/tests/test_shopinvader_variant.py
odoo/addons/shopinvader_sale_profile/views/res_partner.xml
odoo/addons/shopinvader_sale_profile/views/shopinvader_backend.xml
odoo/addons/shopinvader_sale_profile/views/shopinvader_partner.xml
odoo13_addon_shopinvader_sale_profile-13.0.1.3.0.dist-info/METADATA
odoo13_addon_shopinvader_sale_profile-13.0.1.3.0.dist-info/WHEEL
odoo13_addon_shopinvader_sale_profile-13.0.1.3.0.dist-info/top_level.txt
odoo13_addon_shopinvader_sale_profile-13.0.1.3.0.dist-info/RECORD
