Metadata-Version: 2.1
Name: odoo13-addon-shopinvader-sale-profile
Version: 13.0.1.3.0
Summary: ShopInvader - Sale profile
Home-page: https://github.com/shopinvader/odoo-shopinvader
Author: Akretion,ACSONE SA/NV
License: AGPL-3
Platform: UNKNOWN
Classifier: Programming Language :: Python
Classifier: Framework :: Odoo
Classifier: Framework :: Odoo :: 13.0
Classifier: License :: OSI Approved :: GNU Affero General Public License v3
Requires-Python: >=3.5
Requires-Dist: odoo13-addon-shopinvader
Requires-Dist: odoo (<13.1dev,>=13.0a)
